dammy_splunk_packaging_toolkit-1.1.7a0.data/data/LICENSE.txt
slim/__init__.py
slim/__main__.py
slim/config.py
slim/describe.py
slim/generate_manifest.py
slim/package.py
slim/partition.py
slim/update_installation.py
slim/validate.py
slim/app/__init__.py
slim/app/_configuration.py
slim/app/_configuration_spec.py
slim/app/_configuration_validation_plugin.py
slim/app/_configuration_validator.py
slim/app/_deployment.py
slim/app/_installation.py
slim/app/_manifest.py
slim/app/_server_class.py
slim/app/_source.py
slim/app/_internal/__init__.py
slim/app/_internal/file_buffer.py
slim/app/_internal/file_position.py
slim/app/_internal/file_reader.py
slim/app/_internal/json_data.py
slim/app/_internal/named_object.py
slim/app/_internal/object_view.py
slim/app/_internal/ordered_set.py
slim/command/__init__.py
slim/command/public.py
slim/config/common-information-models.json
slim/config/ignore
slim/config/settings
slim/config/splunk-releases.json
slim/config/conf-specs/alert_actions.conf.spec
slim/config/conf-specs/app.conf.spec
slim/config/conf-specs/audit.conf.spec
slim/config/conf-specs/authentication.conf.spec
slim/config/conf-specs/authorize.conf.spec
slim/config/conf-specs/collections.conf.spec
slim/config/conf-specs/commands.conf.spec
slim/config/conf-specs/datamodels.conf.spec
slim/config/conf-specs/datatypesbnf.conf.spec
slim/config/conf-specs/default-mode.conf.spec
slim/config/conf-specs/deployment.conf.spec
slim/config/conf-specs/deploymentclient.conf.spec
slim/config/conf-specs/distsearch.conf.spec
slim/config/conf-specs/event_renderers.conf.spec
slim/config/conf-specs/eventdiscoverer.conf.spec
slim/config/conf-specs/eventtypes.conf.spec
slim/config/conf-specs/fields.conf.spec
slim/config/conf-specs/indexes.conf.spec
slim/config/conf-specs/inputs.conf.spec
slim/config/conf-specs/limits.conf.spec
slim/config/conf-specs/literals.conf.spec
slim/config/conf-specs/livetail.conf.spec
slim/config/conf-specs/macros.conf.spec
slim/config/conf-specs/messages.conf.spec
dammy_splunk_packaging_toolkit-1.1.7a0.dist-info/LICENSE.txt
dammy_splunk_packaging_toolkit-1.1.7a0.dist-info/METADATA
dammy_splunk_packaging_toolkit-1.1.7a0.dist-info/WHEEL
dammy_splunk_packaging_toolkit-1.1.7a0.dist-info/entry_points.txt
dammy_splunk_packaging_toolkit-1.1.7a0.dist-info/top_level.txt
dammy_splunk_packaging_toolkit-1.1.7a0.dist-info/RECORD
