Metadata-Version: 2.1
Name: dammy-splunk-packaging-toolkit
Version: 1.1.7a0
Summary: Dammy-Splunk Packaging Toolkit
Home-page: https://dev.splunk.com
Author: Splunk, Inc.
Author-email: devinfo@splunk.com
License: https://www.splunk.com/en_us/legal/splunk-software-license-agreement.html
Classifier: Programming Language :: Python
Classifier: Development Status :: 5 - Production/Stable
Classifier: Environment :: Other Environment
Classifier: Intended Audience :: Developers
Classifier: License :: Other/Proprietary License
Classifier: Operating System :: OS Independent
Classifier: Topic :: Software Development :: Libraries :: Python Modules
Classifier: Topic :: Software Development :: Libraries :: Application Frameworks
Requires-Python: >=3.5.1,<3.14
License-File: LICENSE.txt
Requires-Dist: semantic_version==2.8.5
Requires-Dist: future>=0.18.3
Requires-Dist: wheel==0.45.1
Requires-Dist: setuptools==75.6.0
